cloud_archiver/__init__.py
cloud_archiver/analyze_directory.py
cloud_archiver/archive_item.py
cloud_archiver/archive_path.py
cloud_archiver/cloud_archiver.py
cloud_archiver/display_archive_items.py
cloud_archiver/display_paths.py
cloud_archiver/file_generator.py
cloud_archiver/get_items_in_archive.py
cloud_archiver/load_config.py
cloud_archiver/transfer_to_achive.py
cloud_archiver/upload_archive.py
cloud_archiver-1.1.3.dist-info/METADATA
cloud_archiver-1.1.3.dist-info/WHEEL
cloud_archiver-1.1.3.dist-info/entry_points.txt
cloud_archiver-1.1.3.dist-info/top_level.txt
cloud_archiver-1.1.3.dist-info/RECORD
