Metadata-Version: 2.1
Name: cloud-archiver
Version: 1.1.3
Summary: A script to detect and archive old folders and files in a directory.
Home-page: https://github.com/pixegami/cloud-archiver
Author: Pixegami
Author-email: pixegami@gmail.com
License: UNKNOWN
Platform: UNKNOWN
Classifier: Programming Language :: Python :: 3.8
Requires-Dist: boto3
Requires-Dist: rich
